{
  "core": "WordPress/WordPress#6.2.2",
  "plugins": [
    "."
  ],
  "config": {
    "WP_DEBUG": true,
    "WP_DEBUG_DISPLAY": true,
    "FS_METHOD": "direct",
    "WP_DEFAULT_THEME": "twentytwentythree"
  },
  "env": {
    "tests": {
      "plugins": [
        "."
      ],
      "mappings": {
          "wp-content/mu-plugins": "./node_modules/@wordpress/e2e-tests/mu-plugins",
          "wp-content/plugins/gutenberg-test-plugins": "./node_modules/@wordpress/e2e-tests/plugins",
          "wp-content/themes/gutenberg-test-themes/twentytwentythree": "https://downloads.wordpress.org/theme/twentytwentythree.1.0.zip"
		}
    }
  }
}
