{
	"$schema": "https://schemas.wp.org/trunk/block.json",
	"apiVersion": 2,
	"name": "themeisle-blocks/countdown",
	"title": "Countdown",
	"category": "themeisle-blocks",
	"description": "Set a countdown for a date. Powered by Otter.",
	"keywords": [ "countdown", "time", "counter" ],
	"textdomain": "otter-blocks",
	"attributes": {
		"id": {
			"type": "string"
		},
		"date": {
			"type": "string"
		},
		"exclude": {
			"type": "array"
		},
		"backgroundColor": {
			"type": "string"
		},
		"valueColor": {
			"type": "string"
		},
		"labelColor": {
			"type": "string"
		},
		"labelDistance": {
			"type": "number"
		},
		"gap": {
			"type": "number"
		},
		"gapTablet": {
			"type": "number"
		},
		"gapMobile": {
			"type": "number"
		},
		"width": {
			"type": "number"
		},
		"widthTablet": {
			"type": "number"
		},
		"widthMobile": {
			"type": "number"
		},
		"height": {
			"type": "number"
		},
		"heightTablet": {
			"type": "number"
		},
		"heightMobile": {
			"type": "number"
		},
		"borderRadius": {
			"type": "number",
			"default": 0
		},
		"borderRadiusType": {
			"type": "string",
			"default": "linked"
		},
		"borderRadiusTopRight": {
			"type": "number",
			"default": 0
		},
		"borderRadiusTopLeft": {
			"type": "number",
			"default": 0
		},
		"borderRadiusBottomRight": {
			"type": "number",
			"default": 0
		},
		"borderRadiusBottomLeft": {
			"type": "number",
			"default": 0
		},
		"borderWidth": {
			"type": "number"
		},
		"borderWidthTablet": {
			"type": "number"
		},
		"borderWidthMobile": {
			"type": "number"
		},
		"borderColor": {
			"type": "string"
		},
		"valueFontSize": {
			"type": "number"
		},
		"valueFontSizeTablet": {
			"type": "number"
		},
		"valueFontSizeMobile": {
			"type": "number"
		},
		"labelFontSize": {
			"type": "number"
		},
		"labelFontSizeTablet": {
			"type": "number"
		},
		"labelFontSizeMobile": {
			"type": "number"
		},
		"hasSeparators": {
			"type": "boolean"
		}
	},
	"supports": {
		"align": [ "wide", "full" ]
	},
	"editorStyle": "otter-countdown-editor",
	"style": "otter-countdown-style",
	"script": "otter-countdown"
}